{
      "Values": {
            "[[array([0, 0, 1, 0, 0]), array([[0, 0, 0],\n       [0, 0, 0],\n       [0, 0, 0],\n       [1, 0, 0],\n       [2, 0, 0],\n       [3, 0, 0]])]]": {
                  "Q": [
                        -602.22,
                        -633.969,
                        -500.0,
                        -500.0,
                        -673.149
                  ],
                  "T": [
                        95,
                        168,
                        0,
                        0,
                        184
                  ]
            },
            "[[array([0, 1, 0, 0, 0]), array([[0, 0, 0],\n       [3, 7, 0],\n       [2, 6, 0],\n       [1, 5, 0],\n       [0, 4, 8],\n       [9, 0, 0]])]]": {
                  "Q": [
                        -605.21,
                        -657.948,
                        -500.0,
                        -500.0,
                        -674.228
                  ],
                  "T": [
                        133,
                        119,
                        0,
                        0,
                        150
                  ]
            },
            "[[array([0, 1, 0, 0, 0]), array([[0, 0, 0],\n       [2, 6, 0],\n       [1, 5, 0],\n       [0, 4, 0],\n       [0, 3, 7],\n       [8, 0, 0]])]]": {
                  "Q": [
                        -559.157,
                        -586.059,
                        -500.0,
                        -500.0,
                        -577.369
                  ],
                  "T": [
                        47,
                        75,
                        0,
                        0,
                        97
                  ]
            },
            "[[array([0, 0, 0, 1, 0]), array([[0, 0, 0],\n       [0, 0, 0],\n       [0, 1, 3],\n       [0, 2, 0],\n       [0, 0, 0],\n       [4, 0, 0]])]]": {
                  "Q": [
                        -561.067,
                        -578.287,
                        -500.0,
                        -500.0,
                        -568.069
                  ],
                  "T": [
                        196,
                        186,
                        0,
                        0,
                        508
                  ]
            },
            "[[array([0, 1, 0, 0, 0]), array([[0, 0, 0],\n       [0, 3, 0],\n       [0, 2, 0],\n       [0, 1, 0],\n       [0, 0, 4],\n       [5, 0, 0]])]]": {
                  "Q": [
                        -567.159,
                        -572.103,
                        -500.0,
                        -500.0,
                        -559.73
                  ],
                  "T": [
                        164,
                        153,
                        0,
                        0,
                        548
                  ]
            },
            "[[array([0, 1, 0, 0, 0]), array([[0, 0, 0],\n       [0, 0, 0],\n       [0, 0, 0],\n       [0, 0, 0],\n       [0, 0, 0],\n       [1, 0, 0]])]]": {
                  "Q": [
                        -566.826,
                        -575.481,
                        -500.0,
                        -500.0,
                        -554.099
                  ],
                  "T": [
                        688,
                        789,
                        0,
                        0,
                        3023
                  ]
            },
            "[[array([0, 0, 0, 1, 0]), array([[0, 0, 0],\n       [2, 0, 0],\n       [1, 3, 5],\n       [0, 4, 0],\n       [0, 0, 0],\n       [6, 0, 0]])]]": {
                  "Q": [
                        -621.176,
                        -661.725,
                        -500.0,
                        -500.0,
                        -663.756
                  ],
                  "T": [
                        223,
                        180,
                        0,
                        0,
                        318
                  ]
            },
            "[[array([0, 0, 1, 0, 0]), array([[0, 0, 0],\n       [0, 0, 0],\n       [0, 0, 0],\n       [0, 0, 0],\n       [0, 0, 0],\n       [1, 0, 0]])]]": {
                  "Q": [
                        -566.676,
                        -573.605,
                        -500.0,
                        -500.0,
                        -574.135
                  ],
                  "T": [
                        751,
                        672,
                        0,
                        0,
                        2718
                  ]
            },
            "[[array([0, 1, 0, 0, 0]), array([[0, 0, 0],\n       [0, 2, 0],\n       [0, 1, 0],\n       [0, 0, 0],\n       [0, 0, 3],\n       [4, 0, 0]])]]": {
                  "Q": [
                        -553.22,
                        -556.589,
                        -500.0,
                        -500.0,
                        -539.38
                  ],
                  "T": [
                        102,
                        181,
                        0,
                        0,
                        592
                  ]
            },
            "[[array([1, 0, 0, 0, 0]), array([[0, 0, 0],\n       [0, 0, 3],\n       [0, 1, 0],\n       [0, 2, 0],\n       [0, 0, 0],\n       [4, 0, 0]])]]": {
                  "Q": [
                        -557.158,
                        -569.3,
                        -500.0,
                        -500.0,
                        -557.949
                  ],
                  "T": [
                        293,
                        328,
                        0,
                        0,
                        1741
                  ]
            },
            "[[array([1, 0, 0, 0, 0]), array([[0, 0, 0],\n       [0, 0, 0],\n       [0, 0, 0],\n       [0, 0, 0],\n       [0, 0, 0],\n       [1, 0, 0]])]]": {
                  "Q": [
                        -557.323,
                        -571.033,
                        -500.0,
                        -500.0,
                        -552.893
                  ],
                  "T": [
                        585,
                        575,
                        0,
                        0,
                        2708
                  ]
            },
            "[[array([0, 0, 0, 0, 1]), array([[0, 0, 0],\n       [0, 0, 0],\n       [0, 1, 0],\n       [0, 0, 0],\n       [0, 0, 0],\n       [2, 0, 0]])]]": {
                  "Q": [
                        -574.888,
                        -603.527,
                        -500.0,
                        -500.0,
                        -638.615
                  ],
                  "T": [
                        351,
                        353,
                        0,
                        0,
                        677
                  ]
            },
            "[[array([1, 0, 0, 0, 0]), array([[0, 0, 0],\n       [0, 4, 7],\n       [1, 5, 0],\n       [2, 6, 0],\n       [3, 0, 0],\n       [8, 0, 0]])]]": {
                  "Q": [
                        -606.351,
                        -685.981,
                        -500.0,
                        -500.0,
                        -696.097
                  ],
                  "T": [
                        172,
                        149,
                        0,
                        0,
                        193
                  ]
            },
            "[[array([0, 0, 0, 1, 0]), array([[0, 0, 0],\n       [0, 0, 0],\n       [0, 0, 0],\n       [0, 0, 0],\n       [0, 0, 0],\n       [1, 0, 0]])]]": {
                  "Q": [
                        -557.427,
                        -566.329,
                        -500.0,
                        -500.0,
                        -550.084
                  ],
                  "T": [
                        498,
                        464,
                        0,
                        0,
                        2423
                  ]
            },
            "[[array([0, 0, 0, 0, 1]), array([[0, 0, 0],\n       [0, 0, 0],\n       [0, 0, 0],\n       [0, 0, 0],\n       [0, 0, 0],\n       [1, 0, 0]])]]": {
                  "Q": [
                        -561.936,
                        -545.998,
                        -500.0,
                        -500.0,
                        -543.719
                  ],
                  "T": [
                        539,
                        506,
                        0,
                        0,
                        1992
                  ]
            },
            "[[array([0, 0, 0, 1, 0]), array([[0, 0, 0],\n       [0, 0, 0],\n       [0, 0, 1],\n       [0, 0, 0],\n       [0, 0, 0],\n       [2, 0, 0]])]]": {
                  "Q": [
                        -531.499,
                        -535.841,
                        -500.0,
                        -500.0,
                        -516.989
                  ],
                  "T": [
                        31,
                        53,
                        0,
                        0,
                        263
                  ]
            },
            "[[array([0, 0, 0, 0, 1]), array([[0, 0, 0],\n       [2, 0, 0],\n       [1, 4, 0],\n       [0, 0, 0],\n       [3, 0, 0],\n       [5, 0, 0]])]]": {
                  "Q": [
                        -531.337,
                        -591.266,
                        -500.0,
                        -500.0,
                        -583.799
                  ],
                  "T": [
                        12,
                        27,
                        0,
                        0,
                        92
                  ]
            }
      },
      "Policy": {}
}