{
      "Values": {
            "[[array([1]), array([[0, 0, 0],\n       [0, 0, 0],\n       [0, 0, 0],\n       [1, 0, 0],\n       [2, 0, 0],\n       [0, 0, 0],\n       [0, 0, 0],\n       [0, 0, 0],\n       [0, 0, 0],\n       [3, 0, 0]])]]": {
                  "Q": [
                        -373.318,
                        -368.608,
                        0,
                        -367.533,
                        -745.41
                  ],
                  "T": [
                        681,
                        684,
                        0,
                        732,
                        311
                  ]
            },
            "[[array([1]), array([[0, 0, 0],\n       [0, 0, 0],\n       [0, 0, 0],\n       [0, 0, 0],\n       [0, 0, 0],\n       [0, 0, 0],\n       [0, 0, 0],\n       [0, 0, 0],\n       [0, 0, 0],\n       [1, 0, 0]])]]": {
                  "Q": [
                        -75.949,
                        -78.168,
                        0,
                        -76.745,
                        -260.2
                  ],
                  "T": [
                        160,
                        103,
                        0,
                        204,
                        65
                  ]
            },
            "[[array([1]), array([[0, 0, 0],\n       [0, 0, 0],\n       [0, 0, 0],\n       [0, 0, 0],\n       [1, 0, 0],\n       [0, 0, 0],\n       [0, 0, 0],\n       [0, 0, 0],\n       [0, 0, 0],\n       [2, 0, 0]])]]": {
                  "Q": [
                        -72.976,
                        -58.198,
                        0,
                        -66.415,
                        -235.5
                  ],
                  "T": [
                        171,
                        131,
                        0,
                        158,
                        56
                  ]
            },
            "[[array([1]), array([[0, 0, 0],\n       [1, 0, 0],\n       [0, 0, 0],\n       [2, 0, 0],\n       [3, 0, 0],\n       [0, 0, 0],\n       [0, 0, 0],\n       [0, 0, 0],\n       [0, 0, 0],\n       [4, 0, 0]])]]": {
                  "Q": [
                        -22.811,
                        -16.298,
                        0,
                        -17.804,
                        -14.969
                  ],
                  "T": [
                        12,
                        7,
                        0,
                        10,
                        3
                  ]
            }
      },
      "Policy": {}
}