{
      "Values": {
            "[[array([0]), [[0, 0, 0], [0, 0, 0], [0, 0, 0], [0, 0, 0], [0, 0, 0], [0, 0, 0], [0, 0, 0], [0, 0, 0]]], [array([0]), [[0, 0, 0], [0, 0, 0], [0, 0, 0], [0, 0, 0], [0, 0, 0], [0, 0, 0], [0, 0, 0], [0, 0, 0]]], [array([1]), array([[0, 0, 0],\n       [0, 0, 0],\n       [0, 0, 0],\n       [0, 0, 0],\n       [0, 0, 0],\n       [0, 0, 0],\n       [0, 0, 0],\n       [1, 0, 0]])], [array([0]), [[0, 0, 0], [0, 0, 0], [0, 0, 0], [0, 0, 0], [0, 0, 0], [0, 0, 0], [0, 0, 0], [0, 0, 0]]], [array([0]), [[0, 0, 0], [0, 0, 0], [0, 0, 0], [0, 0, 0], [0, 0, 0], [0, 0, 0], [0, 0, 0], [0, 0, 0]]]]": {
                  "Q": [
                        386.54,
                        390.725,
                        383.668,
                        390.482,
                        376.001
                  ],
                  "T": [
                        629,
                        642,
                        607,
                        547,
                        601
                  ]
            },
            "[[array([0]), [[0, 0, 0], [0, 0, 0], [0, 0, 0], [0, 0, 0], [0, 0, 0], [0, 0, 0], [0, 0, 0], [0, 0, 0]]], [array([0]), [[0, 0, 0], [0, 0, 0], [0, 0, 0], [0, 0, 0], [0, 0, 0], [0, 0, 0], [0, 0, 0], [0, 0, 0]]], [array([1]), array([[0, 0, 0],\n       [1, 0, 0],\n       [2, 0, 0],\n       [0, 0, 0],\n       [0, 0, 0],\n       [0, 0, 0],\n       [0, 0, 0],\n       [3, 0, 0]])], [array([0]), [[0, 0, 0], [0, 0, 0], [0, 0, 0], [0, 0, 0], [0, 0, 0], [0, 0, 0], [0, 0, 0], [0, 0, 0]]], [array([0]), [[0, 0, 0], [0, 0, 0], [0, 0, 0], [0, 0, 0], [0, 0, 0], [0, 0, 0], [0, 0, 0], [0, 0, 0]]]]": {
                  "Q": [
                        400.389,
                        384.995,
                        355.45,
                        347.835,
                        298.325
                  ],
                  "T": [
                        305,
                        193,
                        147,
                        147,
                        102
                  ]
            }
      },
      "Policy": {
            "[[array([0]), [[0, 0, 0], [0, 0, 0], [0, 0, 0], [0, 0, 0], [0, 0, 0], [0, 0, 0], [0, 0, 0], [0, 0, 0]]], [array([0]), [[0, 0, 0], [0, 0, 0], [0, 0, 0], [0, 0, 0], [0, 0, 0], [0, 0, 0], [0, 0, 0], [0, 0, 0]]], [array([1]), array([[0, 0, 0],\n       [0, 0, 0],\n       [0, 0, 0],\n       [0, 0, 0],\n       [0, 0, 0],\n       [0, 0, 0],\n       [0, 0, 0],\n       [1, 0, 0]])], [array([0]), [[0, 0, 0], [0, 0, 0], [0, 0, 0], [0, 0, 0], [0, 0, 0], [0, 0, 0], [0, 0, 0], [0, 0, 0]]], [array([0]), [[0, 0, 0], [0, 0, 0], [0, 0, 0], [0, 0, 0], [0, 0, 0], [0, 0, 0], [0, 0, 0], [0, 0, 0]]]]": [
                  0.21,
                  0.215,
                  0.207,
                  0.206,
                  0.2
            ],
            "[[array([0]), [[0, 0, 0], [0, 0, 0], [0, 0, 0], [0, 0, 0], [0, 0, 0], [0, 0, 0], [0, 0, 0], [0, 0, 0]]], [array([0]), [[0, 0, 0], [0, 0, 0], [0, 0, 0], [0, 0, 0], [0, 0, 0], [0, 0, 0], [0, 0, 0], [0, 0, 0]]], [array([1]), array([[0, 0, 0],\n       [1, 0, 0],\n       [2, 0, 0],\n       [0, 0, 0],\n       [0, 0, 0],\n       [0, 0, 0],\n       [0, 0, 0],\n       [3, 0, 0]])], [array([0]), [[0, 0, 0], [0, 0, 0], [0, 0, 0], [0, 0, 0], [0, 0, 0], [0, 0, 0], [0, 0, 0], [0, 0, 0]]], [array([0]), [[0, 0, 0], [0, 0, 0], [0, 0, 0], [0, 0, 0], [0, 0, 0], [0, 0, 0], [0, 0, 0], [0, 0, 0]]]]": [
                  0.626,
                  0.188,
                  0.087,
                  0.088,
                  0.051
            ]
      }
}