{
      "Values": {
            "[[array([1]), array([[0, 0, 0],\n       [1, 0, 0],\n       [2, 0, 0],\n       [0, 0, 0],\n       [0, 0, 0],\n       [0, 0, 0],\n       [0, 0, 0],\n       [3, 0, 0]])]]": {
                  "Q": [
                        -28.049,
                        0,
                        0,
                        -42.762,
                        -13.758
                  ],
                  "T": [
                        120,
                        0,
                        0,
                        159,
                        130
                  ]
            },
            "[[array([1]), array([[0, 0, 0],\n       [0, 0, 0],\n       [0, 0, 0],\n       [0, 0, 0],\n       [0, 0, 0],\n       [0, 0, 0],\n       [0, 0, 0],\n       [1, 0, 0]])]]": {
                  "Q": [
                        1.413,
                        0,
                        0,
                        -29.107,
                        -7.386
                  ],
                  "T": [
                        218,
                        0,
                        0,
                        226,
                        223
                  ]
            },
            "[[array([1]), array([[0, 0, 0],\n       [0, 0, 0],\n       [1, 0, 0],\n       [0, 0, 0],\n       [0, 0, 0],\n       [0, 0, 0],\n       [0, 0, 0],\n       [2, 0, 0]])]]": {
                  "Q": [
                        -25.62,
                        0,
                        0,
                        -25.355,
                        -8.215
                  ],
                  "T": [
                        109,
                        0,
                        0,
                        113,
                        111
                  ]
            }
      },
      "Policy": {
            "[[array([1]), array([[0, 0, 0],\n       [1, 0, 0],\n       [2, 0, 0],\n       [0, 0, 0],\n       [0, 0, 0],\n       [0, 0, 0],\n       [0, 0, 0],\n       [3, 0, 0]])]]": [
                  0.2,
                  0.2,
                  0.2,
                  0.198,
                  0.2
            ],
            "[[array([1]), array([[0, 0, 0],\n       [0, 0, 0],\n       [0, 0, 0],\n       [0, 0, 0],\n       [0, 0, 0],\n       [0, 0, 0],\n       [0, 0, 0],\n       [1, 0, 0]])]]": [
                  0.2,
                  0.2,
                  0.2,
                  0.199,
                  0.2
            ],
            "[[array([1]), array([[0, 0, 0],\n       [0, 0, 0],\n       [1, 0, 0],\n       [0, 0, 0],\n       [0, 0, 0],\n       [0, 0, 0],\n       [0, 0, 0],\n       [2, 0, 0]])]]": [
                  0.199,
                  0.2,
                  0.2,
                  0.2,
                  0.2
            ]
      }
}