{
      "Values": {
            "[0 0 1 0 0], [[0 0 0]\n [0 0 0]\n [0 0 0]\n [0 0 0]\n [1 0 0]\n [2 0 0]]": {
                  "Q": [
                        -500.0,
                        -500.0,
                        -525.141,
                        -523.689,
                        -511.764
                  ],
                  "T": [
                        0,
                        0,
                        387,
                        461,
                        1228
                  ]
            },
            "[1 0 0 0 0], [[0 0 0]\n [0 2 5]\n [0 3 0]\n [0 4 0]\n [1 0 0]\n [6 0 0]]": {
                  "Q": [
                        -500.0,
                        -500.0,
                        -529.871,
                        -526.297,
                        -533.063
                  ],
                  "T": [
                        0,
                        0,
                        490,
                        529,
                        1140
                  ]
            },
            "[1 0 0 0 0], [[0 0 0]\n [0 0 1]\n [0 0 0]\n [0 0 0]\n [0 0 0]\n [2 0 0]]": {
                  "Q": [
                        -500.0,
                        -500.0,
                        -474.198,
                        -497.231,
                        -463.804
                  ],
                  "T": [
                        0,
                        0,
                        395,
                        335,
                        2187
                  ]
            },
            "[0 1 0 0 0], [[0 0 0]\n [2 6 0]\n [1 5 0]\n [0 4 0]\n [0 3 7]\n [8 0 0]]": {
                  "Q": [
                        -500.0,
                        -500.0,
                        -524.801,
                        -522.21,
                        -524.525
                  ],
                  "T": [
                        0,
                        0,
                        110,
                        97,
                        264
                  ]
            },
            "[0 1 0 0 0], [[0 0 0]\n [0 0 0]\n [0 0 0]\n [0 0 0]\n [0 0 1]\n [2 0 0]]": {
                  "Q": [
                        -500.0,
                        -500.0,
                        -483.382,
                        -463.695,
                        -472.845
                  ],
                  "T": [
                        0,
                        0,
                        118,
                        407,
                        293
                  ]
            },
            "[0 0 0 1 0], [[0 0 0]\n [3 0 0]\n [2 4 6]\n [0 5 0]\n [1 0 0]\n [7 0 0]]": {
                  "Q": [
                        -500.0,
                        -500.0,
                        -532.472,
                        -528.048,
                        -523.266
                  ],
                  "T": [
                        0,
                        0,
                        440,
                        542,
                        1523
                  ]
            },
            "[0 1 0 0 0], [[0 0 0]\n [0 4 0]\n [0 3 0]\n [0 2 0]\n [0 1 5]\n [6 0 0]]": {
                  "Q": [
                        -500.0,
                        -500.0,
                        -506.94,
                        -495.897,
                        -502.541
                  ],
                  "T": [
                        0,
                        0,
                        393,
                        652,
                        1326
                  ]
            },
            "[0 0 0 1 0], [[0 0 0]\n [0 0 0]\n [0 0 1]\n [0 0 0]\n [0 0 0]\n [2 0 0]]": {
                  "Q": [
                        -500.0,
                        -500.0,
                        -501.141,
                        -500.852,
                        -498.012
                  ],
                  "T": [
                        0,
                        0,
                        168,
                        129,
                        726
                  ]
            },
            "[0 1 0 0 0], [[0 0 0]\n [0 1 0]\n [0 0 0]\n [0 0 0]\n [0 0 2]\n [3 0 0]]": {
                  "Q": [
                        -500.0,
                        -500.0,
                        -449.513,
                        -497.681,
                        -468.534
                  ],
                  "T": [
                        0,
                        0,
                        364,
                        124,
                        450
                  ]
            },
            "[0 0 0 0 1], [[0 0 0]\n [2 0 0]\n [1 4 0]\n [0 0 0]\n [3 0 0]\n [5 0 0]]": {
                  "Q": [
                        -500.0,
                        -500.0,
                        -543.08,
                        -538.951,
                        -541.317
                  ],
                  "T": [
                        0,
                        0,
                        156,
                        176,
                        260
                  ]
            },
            "[0 1 0 0 0], [[ 0  0  0]\n [ 4  8  0]\n [ 3  7  0]\n [ 2  6  0]\n [ 1  5  9]\n [10  0  0]]": {
                  "Q": [
                        -500.0,
                        -500.0,
                        -547.32,
                        -542.148,
                        -545.59
                  ],
                  "T": [
                        0,
                        0,
                        242,
                        280,
                        630
                  ]
            },
            "[1 0 0 0 0], [[0 0 0]\n [0 1 4]\n [0 2 0]\n [0 3 0]\n [0 0 0]\n [5 0 0]]": {
                  "Q": [
                        -500.0,
                        -500.0,
                        -500.134,
                        -501.58,
                        -497.833
                  ],
                  "T": [
                        0,
                        0,
                        120,
                        78,
                        481
                  ]
            },
            "[0 0 0 0 1], [[0 0 0]\n [1 0 0]\n [0 3 0]\n [0 0 0]\n [2 0 0]\n [4 0 0]]": {
                  "Q": [
                        -500.0,
                        -500.0,
                        -514.499,
                        -512.679,
                        -516.498
                  ],
                  "T": [
                        0,
                        0,
                        83,
                        55,
                        85
                  ]
            },
            "[0 0 0 1 0], [[0 0 0]\n [1 0 0]\n [0 2 4]\n [0 3 0]\n [0 0 0]\n [5 0 0]]": {
                  "Q": [
                        -500.0,
                        -500.0,
                        -510.33,
                        -504.457,
                        -513.518
                  ],
                  "T": [
                        0,
                        0,
                        130,
                        87,
                        259
                  ]
            },
            "[0 0 0 0 1], [[0 0 0]\n [0 0 0]\n [0 2 0]\n [0 0 0]\n [1 0 0]\n [3 0 0]]": {
                  "Q": [
                        -500.0,
                        -500.0,
                        -516.287,
                        -509.821,
                        -504.145
                  ],
                  "T": [
                        0,
                        0,
                        204,
                        352,
                        763
                  ]
            },
            "[0 1 0 0 0], [[0 0 0]\n [1 5 0]\n [0 4 0]\n [0 3 0]\n [0 2 6]\n [7 0 0]]": {
                  "Q": [
                        -500.0,
                        -500.0,
                        -508.487,
                        -508.314,
                        -508.923
                  ],
                  "T": [
                        0,
                        0,
                        99,
                        90,
                        182
                  ]
            },
            "[0 0 1 0 0], [[0 0 0]\n [1 0 0]\n [0 0 0]\n [2 0 0]\n [3 0 0]\n [4 0 0]]": {
                  "Q": [
                        -500.0,
                        -500.0,
                        -505.659,
                        -504.153,
                        -504.542
                  ],
                  "T": [
                        0,
                        0,
                        23,
                        18,
                        30
                  ]
            },
            "[1 0 0 0 0], [[0 0 0]\n [1 5 8]\n [2 6 0]\n [3 7 0]\n [4 0 0]\n [9 0 0]]": {
                  "Q": [
                        -500.0,
                        -500.0,
                        -505.982,
                        -506.124,
                        -505.957
                  ],
                  "T": [
                        0,
                        0,
                        18,
                        13,
                        13
                  ]
            },
            "[0 1 0 0 0], [[0 0 0]\n [0 2 0]\n [0 1 0]\n [0 0 0]\n [0 0 3]\n [4 0 0]]": {
                  "Q": [
                        -500.0,
                        -500.0,
                        -498.57,
                        -499.286,
                        -492.984
                  ],
                  "T": [
                        0,
                        0,
                        108,
                        53,
                        222
                  ]
            }
      },
      "Policy": {}
}