{
      "Values": {
            "[[array([0, 0, 0, 1, 0]), array([[0, 0, 0],\n       [2, 0, 0],\n       [1, 3, 5],\n       [0, 4, 0],\n       [0, 0, 0],\n       [6, 0, 0]])]]": {
                  "Q": [
                        -192.209,
                        -59.324,
                        -500.0,
                        -123.081,
                        203.523
                  ],
                  "T": [
                        184,
                        286,
                        0,
                        218,
                        1397
                  ]
            },
            "[[array([0, 0, 1, 0, 0]), array([[0, 0, 0],\n       [0, 0, 0],\n       [0, 0, 0],\n       [0, 0, 0],\n       [0, 0, 0],\n       [1, 0, 0]])]]": {
                  "Q": [
                        -83.855,
                        -144.723,
                        -500.0,
                        -52.82,
                        102.648
                  ],
                  "T": [
                        486,
                        511,
                        0,
                        531,
                        3360
                  ]
            },
            "[[array([1, 0, 0, 0, 0]), array([[0, 0, 0],\n       [0, 1, 4],\n       [0, 2, 0],\n       [0, 3, 0],\n       [0, 0, 0],\n       [5, 0, 0]])]]": {
                  "Q": [
                        -203.158,
                        -177.111,
                        -500.0,
                        -199.101,
                        -58.849
                  ],
                  "T": [
                        212,
                        261,
                        0,
                        157,
                        1238
                  ]
            },
            "[[array([0, 1, 0, 0, 0]), array([[0, 0, 0],\n       [0, 0, 0],\n       [0, 0, 0],\n       [0, 0, 0],\n       [0, 0, 0],\n       [1, 0, 0]])]]": {
                  "Q": [
                        -317.299,
                        -149.221,
                        -500.0,
                        -278.555,
                        -320.643
                  ],
                  "T": [
                        238,
                        554,
                        0,
                        765,
                        270
                  ]
            },
            "[[array([0, 0, 1, 0, 0]), array([[0, 0, 0],\n       [1, 0, 0],\n       [0, 0, 0],\n       [2, 0, 0],\n       [3, 0, 0],\n       [4, 0, 0]])]]": {
                  "Q": [
                        -411.919,
                        -290.451,
                        -500.0,
                        -405.119,
                        -462.664
                  ],
                  "T": [
                        52,
                        95,
                        0,
                        31,
                        33
                  ]
            },
            "[[array([0, 0, 0, 1, 0]), array([[0, 0, 0],\n       [0, 0, 0],\n       [0, 1, 3],\n       [0, 2, 0],\n       [0, 0, 0],\n       [4, 0, 0]])]]": {
                  "Q": [
                        -310.55,
                        -265.281,
                        -500.0,
                        -218.562,
                        -52.609
                  ],
                  "T": [
                        91,
                        131,
                        0,
                        163,
                        792
                  ]
            },
            "[[array([0, 0, 0, 1, 0]), array([[0, 0, 0],\n       [0, 0, 0],\n       [0, 0, 1],\n       [0, 0, 0],\n       [0, 0, 0],\n       [2, 0, 0]])]]": {
                  "Q": [
                        -278.813,
                        -222.0,
                        -500.0,
                        -260.034,
                        -93.773
                  ],
                  "T": [
                        131,
                        195,
                        0,
                        153,
                        1082
                  ]
            },
            "[[array([0, 0, 0, 0, 1]), array([[0, 0, 0],\n       [0, 0, 0],\n       [0, 0, 0],\n       [0, 0, 0],\n       [0, 0, 0],\n       [1, 0, 0]])]]": {
                  "Q": [
                        -286.037,
                        -162.316,
                        -500.0,
                        -297.047,
                        -346.898
                  ],
                  "T": [
                        173,
                        401,
                        0,
                        176,
                        148
                  ]
            },
            "[[array([1, 0, 0, 0, 0]), array([[0, 0, 0],\n       [0, 0, 1],\n       [0, 0, 0],\n       [0, 0, 0],\n       [0, 0, 0],\n       [2, 0, 0]])]]": {
                  "Q": [
                        -369.196,
                        -176.508,
                        -500.0,
                        -360.052,
                        -263.406
                  ],
                  "T": [
                        89,
                        346,
                        0,
                        89,
                        281
                  ]
            },
            "[[array([0, 1, 0, 0, 0]), array([[0, 0, 0],\n       [2, 6, 0],\n       [1, 5, 0],\n       [0, 4, 0],\n       [0, 3, 7],\n       [8, 0, 0]])]]": {
                  "Q": [
                        -145.057,
                        -219.455,
                        -500.0,
                        -342.194,
                        -266.875
                  ],
                  "T": [
                        403,
                        256,
                        0,
                        93,
                        229
                  ]
            },
            "[[array([1, 0, 0, 0, 0]), array([[0, 0, 0],\n       [0, 0, 3],\n       [0, 1, 0],\n       [0, 2, 0],\n       [0, 0, 0],\n       [4, 0, 0]])]]": {
                  "Q": [
                        -279.488,
                        -174.92,
                        -500.0,
                        -116.109,
                        38.797
                  ],
                  "T": [
                        181,
                        248,
                        0,
                        236,
                        1509
                  ]
            },
            "[[array([0, 0, 0, 0, 1]), array([[0, 0, 0],\n       [1, 0, 0],\n       [0, 3, 0],\n       [0, 0, 0],\n       [2, 0, 0],\n       [4, 0, 0]])]]": {
                  "Q": [
                        -361.463,
                        -350.105,
                        -500.0,
                        -396.967,
                        -253.517
                  ],
                  "T": [
                        64,
                        57,
                        0,
                        37,
                        330
                  ]
            },
            "[[array([0, 0, 0, 0, 1]), array([[0, 0, 0],\n       [0, 0, 0],\n       [0, 1, 0],\n       [0, 0, 0],\n       [0, 0, 0],\n       [2, 0, 0]])]]": {
                  "Q": [
                        -190.841,
                        -267.485,
                        -500.0,
                        -283.962,
                        -182.255
                  ],
                  "T": [
                        309,
                        146,
                        0,
                        146,
                        533
                  ]
            },
            "[[array([0, 1, 0, 0, 0]), array([[0, 0, 0],\n       [0, 1, 0],\n       [0, 0, 0],\n       [0, 0, 0],\n       [0, 0, 2],\n       [3, 0, 0]])]]": {
                  "Q": [
                        -389.964,
                        -354.446,
                        -500.0,
                        -463.911,
                        -460.265
                  ],
                  "T": [
                        49,
                        96,
                        0,
                        21,
                        53
                  ]
            },
            "[[array([0, 1, 0, 0, 0]), array([[0, 0, 0],\n       [0, 2, 0],\n       [0, 1, 0],\n       [0, 0, 0],\n       [0, 0, 3],\n       [4, 0, 0]])]]": {
                  "Q": [
                        -282.982,
                        -188.808,
                        -500.0,
                        -321.844,
                        -225.87
                  ],
                  "T": [
                        146,
                        611,
                        0,
                        136,
                        404
                  ]
            },
            "[[array([0, 0, 0, 1, 0]), array([[0, 0, 0],\n       [1, 0, 0],\n       [0, 2, 4],\n       [0, 3, 0],\n       [0, 0, 0],\n       [5, 0, 0]])]]": {
                  "Q": [
                        -324.365,
                        -262.861,
                        -500.0,
                        -294.492,
                        -112.704
                  ],
                  "T": [
                        79,
                        118,
                        0,
                        81,
                        585
                  ]
            },
            "[[array([1, 0, 0, 0, 0]), array([[0, 0, 0],\n       [0, 0, 0],\n       [0, 0, 0],\n       [0, 0, 0],\n       [0, 0, 0],\n       [1, 0, 0]])]]": {
                  "Q": [
                        -299.118,
                        -260.808,
                        -500.0,
                        -304.091,
                        -235.207
                  ],
                  "T": [
                        189,
                        214,
                        0,
                        263,
                        1231
                  ]
            },
            "[[array([0, 0, 0, 1, 0]), array([[0, 0, 0],\n       [0, 0, 0],\n       [0, 0, 0],\n       [0, 0, 0],\n       [0, 0, 0],\n       [1, 0, 0]])]]": {
                  "Q": [
                        -231.495,
                        -181.742,
                        -500.0,
                        -176.506,
                        -85.679
                  ],
                  "T": [
                        294,
                        359,
                        0,
                        399,
                        2081
                  ]
            },
            "[[array([0, 1, 0, 0, 0]), array([[0, 0, 0],\n       [1, 5, 0],\n       [0, 4, 0],\n       [0, 3, 0],\n       [0, 2, 6],\n       [7, 0, 0]])]]": {
                  "Q": [
                        -323.46,
                        -287.284,
                        -500.0,
                        -337.683,
                        -20.202
                  ],
                  "T": [
                        86,
                        102,
                        0,
                        70,
                        562
                  ]
            },
            "[[array([1, 0, 0, 0, 0]), array([[0, 0, 0],\n       [1, 5, 8],\n       [2, 6, 0],\n       [3, 7, 0],\n       [4, 0, 0],\n       [9, 0, 0]])]]": {
                  "Q": [
                        -462.599,
                        -391.58,
                        -500.0,
                        -447.854,
                        -476.081
                  ],
                  "T": [
                        15,
                        46,
                        0,
                        20,
                        37
                  ]
            },
            "[[array([1, 0, 0, 0, 0]), array([[0, 0, 0],\n       [0, 4, 7],\n       [1, 5, 0],\n       [2, 6, 0],\n       [3, 0, 0],\n       [8, 0, 0]])]]": {
                  "Q": [
                        -262.575,
                        -240.179,
                        -500.0,
                        -242.321,
                        78.311
                  ],
                  "T": [
                        103,
                        106,
                        0,
                        118,
                        713
                  ]
            },
            "[[array([0, 0, 0, 0, 1]), array([[0, 0, 0],\n       [2, 0, 0],\n       [1, 4, 0],\n       [0, 0, 0],\n       [3, 0, 0],\n       [5, 0, 0]])]]": {
                  "Q": [
                        -425.776,
                        -404.766,
                        -500.0,
                        -443.188,
                        -355.683
                  ],
                  "T": [
                        25,
                        44,
                        0,
                        41,
                        194
                  ]
            }
      },
      "Policy": {}
}