{
      "Values": {
            "[[array([1]), array([[0, 0, 0],\n       [0, 0, 0],\n       [1, 0, 0],\n       [0, 0, 0],\n       [0, 0, 0],\n       [0, 0, 0],\n       [0, 0, 0],\n       [2, 0, 0]])]]": {
                  "Q": [
                        0,
                        -142.142,
                        -118.597,
                        -163.22,
                        -120.831
                  ],
                  "T": [
                        0,
                        191,
                        761,
                        198,
                        295
                  ]
            },
            "[[array([1]), array([[0, 0, 0],\n       [0, 0, 0],\n       [0, 0, 0],\n       [0, 0, 0],\n       [0, 0, 0],\n       [0, 0, 0],\n       [0, 0, 0],\n       [1, 0, 0]])]]": {
                  "Q": [
                        0,
                        -134.785,
                        -137.881,
                        -136.885,
                        -135.092
                  ],
                  "T": [
                        0,
                        180,
                        131,
                        160,
                        601
                  ]
            }
      },
      "Policy": {}
}