{
      "Values": {
            "[[array([1]), array([[0, 0, 0],\n       [0, 0, 0],\n       [0, 0, 0],\n       [1, 0, 0],\n       [2, 0, 0],\n       [0, 0, 0],\n       [0, 0, 0],\n       [0, 0, 0],\n       [0, 0, 0],\n       [3, 0, 0]])]]": {
                  "Q": [
                        -45.599,
                        0,
                        -79.478,
                        -85.8,
                        -44.702
                  ],
                  "T": [
                        179,
                        0,
                        127,
                        124,
                        636
                  ]
            },
            "[[array([1]), array([[0, 0, 0],\n       [0, 0, 0],\n       [0, 0, 0],\n       [0, 0, 0],\n       [0, 0, 0],\n       [0, 0, 0],\n       [0, 0, 0],\n       [0, 0, 0],\n       [0, 0, 0],\n       [1, 0, 0]])]]": {
                  "Q": [
                        -122.902,
                        0,
                        -103.068,
                        -118.251,
                        -103.268
                  ],
                  "T": [
                        578,
                        0,
                        678,
                        556,
                        2687
                  ]
            },
            "[[array([1]), array([[0, 0, 0],\n       [0, 0, 0],\n       [0, 0, 0],\n       [0, 0, 0],\n       [1, 0, 0],\n       [0, 0, 0],\n       [0, 0, 0],\n       [0, 0, 0],\n       [0, 0, 0],\n       [2, 0, 0]])]]": {
                  "Q": [
                        -18.03,
                        0,
                        -10.429,
                        -31.823,
                        -7.687
                  ],
                  "T": [
                        51,
                        0,
                        34,
                        53,
                        244
                  ]
            }
      },
      "Policy": {}
}