{
      "Values": {
            "[[array([0]), [[0, 0, 0], [0, 0, 0], [0, 0, 0], [0, 0, 0], [0, 0, 0], [0, 0, 0], [0, 0, 0], [0, 0, 0]]], [array([0]), [[0, 0, 0], [0, 0, 0], [0, 0, 0], [0, 0, 0], [0, 0, 0], [0, 0, 0], [0, 0, 0], [0, 0, 0]]], [array([1]), array([[0, 0, 0],\n       [1, 0, 0],\n       [2, 0, 0],\n       [0, 0, 0],\n       [0, 0, 0],\n       [0, 0, 0],\n       [0, 0, 0],\n       [3, 0, 0]])]]": {
                  "Q": [
                        105.363,
                        0,
                        0,
                        403.802,
                        75.318
                  ],
                  "T": [
                        44,
                        0,
                        0,
                        35,
                        28
                  ]
            },
            "[[array([0]), [[0, 0, 0], [0, 0, 0], [0, 0, 0], [0, 0, 0], [0, 0, 0], [0, 0, 0], [0, 0, 0], [0, 0, 0]]], [array([0]), [[0, 0, 0], [0, 0, 0], [0, 0, 0], [0, 0, 0], [0, 0, 0], [0, 0, 0], [0, 0, 0], [0, 0, 0]]], [array([1]), array([[0, 0, 0],\n       [0, 0, 0],\n       [0, 0, 0],\n       [0, 0, 0],\n       [0, 0, 0],\n       [0, 0, 0],\n       [0, 0, 0],\n       [1, 0, 0]])]]": {
                  "Q": [
                        474.298,
                        0,
                        0,
                        747.066,
                        475.669
                  ],
                  "T": [
                        121,
                        0,
                        0,
                        511,
                        160
                  ]
            },
            "[[array([0]), [[0, 0, 0], [0, 0, 0], [0, 0, 0], [0, 0, 0], [0, 0, 0], [0, 0, 0], [0, 0, 0], [0, 0, 0]]], [array([0]), [[0, 0, 0], [0, 0, 0], [0, 0, 0], [0, 0, 0], [0, 0, 0], [0, 0, 0], [0, 0, 0], [0, 0, 0]]], [array([1]), array([[0, 0, 0],\n       [0, 0, 0],\n       [1, 0, 0],\n       [0, 0, 0],\n       [0, 0, 0],\n       [0, 0, 0],\n       [0, 0, 0],\n       [2, 0, 0]])]]": {
                  "Q": [
                        66.217,
                        0,
                        0,
                        95.946,
                        28.061
                  ],
                  "T": [
                        20,
                        0,
                        0,
                        20,
                        20
                  ]
            }
      },
      "Policy": {}
}